[
  {
    "id": "1",
    "title": "Secvențe Escape în C++",
    "content": "Explicație detaliată a secvențelor escape și utilizarea lor în C++",
    "tags": [
      "C++",
      "caractere",
      "string",
      "escape",
      "ASCII",
      "sintaxă"
    ]
  },
  {
    "id": "2",
    "title": "Secvențe Escape în C++ - Introducere",
    "content": "Secvențele escape sunt succesiuni de caractere care au alt înțeles decât cel direct atunci când sunt folosite într-un literal caracter sau șir de caractere. Ele încep cu caracterul \\ (backslash) și sunt înlocuite cu caractere care nu ar putea fi folosite în mod direct.",
    "tags": [
      "C++",
      "caractere",
      "string",
      "escape",
      "ASCII",
      "sintaxă"
    ]
  },
  {
    "id": "3",
    "title": "Secvențe Escape în C++ - Necesitatea Secvențelor Escape",
    "content": "Secvențele escape sunt necesare pentru a reprezenta caractere speciale sau caractere care ar avea alt înțeles în cod. De exemplu, pentru a include ghilimele în interiorul unui șir de caractere, trebuie să folosim secvența escape \\\".",
    "tags": [
      "C++",
      "caractere",
      "string",
      "escape",
      "ASCII",
      "sintaxă"
    ]
  },
  {
    "id": "4",
    "title": "Secvențe Escape în C++ - Lista Secvențelor Escape",
    "content": "",
    "tags": [
      "C++",
      "caractere",
      "string",
      "escape",
      "ASCII",
      "sintaxă"
    ]
  },
  {
    "id": "5",
    "title": "Secvențe Escape în C++ - Lista Secvențelor Escape - Secvențe de Bază",
    "content": "\\a - Alertă, Beep (7)\n\\b - Backspace (8)\n\\e - Escape (27)\n\\f - Formfeed (12)\n\\n - NewLine (10)\n\\r - Carriage Return (13)\n\\t - Tab orizontal (9)\n\\v - Tab vertical (11)\n\\\\ - Backslash (92)\n\\\" - Ghilimele (34)\n\\' - Apostrof (39)\n\\? - Semn de întrebare (63)\n\\0 - Caracterul nul (0)",
    "tags": [
      "C++",
      "caractere",
      "string",
      "escape",
      "ASCII",
      "sintaxă"
    ]
  },
  {
    "id": "6",
    "title": "Secvențe Escape în C++ - Lista Secvențelor Escape - Secvențe Numerice",
    "content": "\\nnn - Caracterul cu codul egal cu valoarea octală nnn\n\\xhh - Caracterul cu codul egal cu valoarea hexazecimală hh",
    "tags": [
      "C++",
      "caractere",
      "string",
      "escape",
      "ASCII",
      "sintaxă"
    ]
  },
  {
    "id": "7",
    "title": "Secvențe Escape în C++ - Exemple de Utilizare",
    "content": "",
    "tags": [
      "C++",
      "caractere",
      "string",
      "escape",
      "ASCII",
      "sintaxă"
    ]
  },
  {
    "id": "8",
    "title": "Secvențe Escape în C++ - Exemple de Utilizare - Ghilimele în Șiruri",
    "content": "#include <iostream>\nusing namespace std;\nint main() {\n    cout << \"Hamlet a spus \\\"A fi, sau a nu fi\\\".\";\n    return 0;\n}",
    "tags": [
      "C++",
      "caractere",
      "string",
      "escape",
      "ASCII",
      "sintaxă"
    ]
  },
  {
    "id": "9",
    "title": "Secvențe Escape în C++ - Exemple de Utilizare - Trecere la Rând Nou",
    "content": "#include <iostream>\nusing namespace std;\nint main() {\n    cout << \"Vrei 10 la info?\\nHai pe pbinfo\";\n    return 0;\n}",
    "tags": [
      "C++",
      "caractere",
      "string",
      "escape",
      "ASCII",
      "sintaxă"
    ]
  },
  {
    "id": "10",
    "title": "Secvențe Escape în C++ - Exemple de Utilizare - Variante de Utilizare",
    "content": "Secvența escape poate fi folosită:\n1. Într-un caracter: '\\n'\n2. Într-un șir de caractere: \"\\n\"\n3. Ca parte a unui șir mai lung: \"Text\\nAlt text\"",
    "tags": [
      "C++",
      "caractere",
      "string",
      "escape",
      "ASCII",
      "sintaxă"
    ]
  },
  {
    "id": "11",
    "title": "Secvențe Escape în C++ - Observații Importante",
    "content": "1. Toate secvențele escape încep cu \\\n2. Sunt folosite în constante literale de tip caracter sau șir\n3. Permit reprezentarea caracterelor speciale\n4. Sunt necesare pentru caractere care ar avea alt înțeles în cod\n5. Pot fi folosite pentru reprezentarea caracterelor non-ASCII",
    "tags": [
      "C++",
      "caractere",
      "string",
      "escape",
      "ASCII",
      "sintaxă"
    ]
  },
  {
    "id": "12",
    "title": "Secvențe Escape în C++ - Best Practices",
    "content": "1. Folosiți secvențele escape pentru caractere speciale\n2. Evitați caracterele non-ASCII directe în cod\n3. Documentați utilizarea secvențelor complexe\n4. Verificați compatibilitatea între sisteme\n5. Folosiți secvențele standard când este posibil",
    "tags": [
      "C++",
      "caractere",
      "string",
      "escape",
      "ASCII",
      "sintaxă"
    ]
  }
]